lplangid/const_data.py
lplangid/count_utils.py
lplangid/count_utils_test.py
lplangid/language_classifier.py
lplangid/language_classifier_test.py
lplangid/tokenizer.py
lplangid/tokenizer_test.py
lplangid/freq_data/ar_char_freq.csv
lplangid/freq_data/ar_term_rank.csv
lplangid/freq_data/de_char_freq.csv
lplangid/freq_data/de_term_rank.csv
lplangid/freq_data/el_char_freq.csv
lplangid/freq_data/el_term_rank.csv
lplangid/freq_data/en_char_freq.csv
lplangid/freq_data/en_term_rank.csv
lplangid/freq_data/es_char_freq.csv
lplangid/freq_data/es_term_rank.csv
lplangid/freq_data/fr_char_freq.csv
lplangid/freq_data/fr_term_rank.csv
lplangid/freq_data/he_char_freq.csv
lplangid/freq_data/he_term_rank.csv
lplangid/freq_data/hi_char_freq.csv
lplangid/freq_data/hi_term_rank.csv
lplangid/freq_data/hr_char_freq.csv
lplangid/freq_data/hr_term_rank.csv
lplangid/freq_data/id_char_freq.csv
lplangid/freq_data/id_term_rank.csv
lplangid/freq_data/it_char_freq.csv
lplangid/freq_data/it_term_rank.csv
lplangid/freq_data/ja_char_freq.csv
lplangid/freq_data/ja_term_rank.csv
lplangid/freq_data/ko_char_freq.csv
lplangid/freq_data/ko_term_rank.csv
lplangid/freq_data/mk_char_freq.csv
lplangid/freq_data/mk_term_rank.csv
lplangid/freq_data/ms_char_freq.csv
lplangid/freq_data/ms_term_rank.csv
lplangid/freq_data/nl_char_freq.csv
lplangid/freq_data/nl_term_rank.csv
lplangid/freq_data/pl_char_freq.csv
lplangid/freq_data/pl_term_rank.csv
lplangid/freq_data/pt_char_freq.csv
lplangid/freq_data/pt_term_rank.csv
lplangid/freq_data/ru_char_freq.csv
lplangid/freq_data/ru_term_rank.csv
lplangid/freq_data/sl_char_freq.csv
lplangid/freq_data/sl_term_rank.csv
lplangid/freq_data/sq_char_freq.csv
lplangid/freq_data/sq_term_rank.csv
lplangid/freq_data/sr_char_freq.csv
lplangid/freq_data/sr_term_rank.csv
lplangid/freq_data/th_char_freq.csv
lplangid/freq_data/th_term_rank.csv
lplangid/freq_data/tl_char_freq.csv
lplangid/freq_data/tl_term_rank.csv
lplangid/freq_data/vi_char_freq.csv
lplangid/freq_data/vi_term_rank.csv
lplangid-0.1.4.dist-info/LICENSE
lplangid-0.1.4.dist-info/METADATA
lplangid-0.1.4.dist-info/WHEEL
lplangid-0.1.4.dist-info/top_level.txt
lplangid-0.1.4.dist-info/RECORD
