Metadata-Version: 2.1
Name: lplangid
Version: 0.1.4
Summary: LivePerson language detection package using a Reciprocal Rank Classifier
Home-page: https://github.com/LivePersonInc/lplangid
Author: Dominic Widdows, Chris Brew
Author-email: dwiddows@gmail.com,cbrew@acm.org
License: UNKNOWN
Keywords: language detection,language classification,reciprocal rank classifier,lplangid
Platform: UNKNOWN
License-File: LICENSE
